KeyisBLogging/__init__.py
KeyisBLogging-1.0.7.dist-info/LICENSE
KeyisBLogging-1.0.7.dist-info/METADATA
KeyisBLogging-1.0.7.dist-info/WHEEL
KeyisBLogging-1.0.7.dist-info/top_level.txt
KeyisBLogging-1.0.7.dist-info/RECORD
