Metadata-Version: 2.1
Name: KeyisBLogging
Version: 1.0.7
Summary: KeyisBLogging
Home-page: https://github.com/KeyisB/libs/tree/main/KeyisBLogging
Author: KeyisB
Author-email: keyisb.pip@gmail.com
License: MMB License v1.0
Classifier: Programming Language :: Python :: 3
Classifier: Operating System :: OS Independent
Requires-Python: >=3.12
License-File: LICENSE
Requires-Dist: colorama
